{
  "1000BONKUSDT": {
    "long": [],
    "short": [
      {
        "zone": [
          0.035836,
          0.035872
        ],
        "sl": 0.036443,
        "tp": 0.034122,
        "leverage": 12,
        "po": "Пробой",
        "ATR": 0.005712,
        "ATR_rem": 0.00496,
        "price": 0.034154,
        "rsi": 57.9,
        "macd": 0.000358,
        "macd_signal": 0.000429
      },
      {
        "zone": [
          0.035435,
          0.035471
        ],
        "sl": 0.036042,
        "tp": 0.033721,
        "leverage": 12,
        "po": "Пробой",
        "ATR": 0.005712,
        "ATR_rem": 0.00496,
        "price": 0.034154,
        "rsi": 57.9,
        "macd": 0.000358,
        "macd_signal": 0.000429
      },
      {
        "zone": [
          0.035636,
          0.035671
        ],
        "sl": 0.036242,
        "tp": 0.033922,
        "leverage": 12,
        "po": "Пробой",
        "ATR": 0.005712,
        "ATR_rem": 0.00496,
        "price": 0.034154,
        "rsi": 57.9,
        "macd": 0.000358,
        "macd_signal": 0.000429
      },
      {
        "zone": [
          0.038138,
          0.038176
        ],
        "sl": 0.038747,
        "tp": 0.036424,
        "leverage": 12,
        "po": "Пробой",
        "ATR": 0.005712,
        "ATR_rem": 0.00496,
        "price": 0.034154,
        "rsi": 57.9,
        "macd": 0.000358,
        "macd_signal": 0.000429
      },
      {
        "zone": [
          0.037137,
          0.037174
        ],
        "sl": 0.037745,
        "tp": 0.035423,
        "leverage": 12,
        "po": "Пробой",
        "ATR": 0.005712,
        "ATR_rem": 0.00496,
        "price": 0.034154,
        "rsi": 57.9,
        "macd": 0.000358,
        "macd_signal": 0.000429
      },
      {
        "zone": [
          0.034635,
          0.034669
        ],
        "sl": 0.03524,
        "tp": 0.032921,
        "leverage": 12,
        "po": "Пробой",
        "ATR": 0.005712,
        "ATR_rem": 0.00496,
        "price": 0.034154,
        "rsi": 57.9,
        "macd": 0.000358,
        "macd_signal": 0.000429
      },
      {
        "zone": [
          0.034735,
          0.034769
        ],
        "sl": 0.03534,
        "tp": 0.033021,
        "leverage": 12,
        "po": "Пробой",
        "ATR": 0.005712,
        "ATR_rem": 0.00496,
        "price": 0.034154,
        "rsi": 57.9,
        "macd": 0.000358,
        "macd_signal": 0.000429
      }
    ]
  },
  "AI16ZUSDT": {
    "long": [],
    "short": [
      {
        "zone": [
          0.215916,
          0.216131
        ],
        "sl": 0.217979,
        "tp": 0.210372,
        "leverage": 12,
        "po": "Пробой",
        "ATR": 0.01848,
        "ATR_rem": 0.01498,
        "price": 0.175,
        "rsi": 58.48,
        "macd": 0.002729,
        "macd_signal": 0.003872
      },
      {
        "zone": [
          0.187788,
          0.187975
        ],
        "sl": 0.189823,
        "tp": 0.182244,
        "leverage": 12,
        "po": "Пробой",
        "ATR": 0.01848,
        "ATR_rem": 0.01498,
        "price": 0.175,
        "rsi": 58.48,
        "macd": 0.002729,
        "macd_signal": 0.003872
      },
      {
        "zone": [
          0.18979,
          0.189979
        ],
        "sl": 0.191827,
        "tp": 0.184246,
        "leverage": 12,
        "po": "Пробой",
        "ATR": 0.01848,
        "ATR_rem": 0.01498,
        "price": 0.175,
        "rsi": 58.48,
        "macd": 0.002729,
        "macd_signal": 0.003872
      },
      {
        "zone": [
          0.199299,
          0.199498
        ],
        "sl": 0.201346,
        "tp": 0.193755,
        "leverage": 12,
        "po": "Пробой",
        "ATR": 0.01848,
        "ATR_rem": 0.01498,
        "price": 0.175,
        "rsi": 58.48,
        "macd": 0.002729,
        "macd_signal": 0.003872
      },
      {
        "zone": [
          0.211411,
          0.211622
        ],
        "sl": 0.21347,
        "tp": 0.205867,
        "leverage": 12,
        "po": "Пробой",
        "ATR": 0.01848,
        "ATR_rem": 0.01498,
        "price": 0.175,
        "rsi": 58.48,
        "macd": 0.002729,
        "macd_signal": 0.003872
      },
      {
        "zone": [
          0.193193,
          0.193386
        ],
        "sl": 0.195234,
        "tp": 0.187649,
        "leverage": 12,
        "po": "Пробой",
        "ATR": 0.01848,
        "ATR_rem": 0.01498,
        "price": 0.175,
        "rsi": 58.48,
        "macd": 0.002729,
        "macd_signal": 0.003872
      },
      {
        "zone": [
          0.184885,
          0.185069
        ],
        "sl": 0.186917,
        "tp": 0.179341,
        "leverage": 12,
        "po": "Пробой",
        "ATR": 0.01848,
        "ATR_rem": 0.01498,
        "price": 0.175,
        "rsi": 58.48,
        "macd": 0.002729,
        "macd_signal": 0.003872
      },
      {
        "zone": [
          0.197097,
          0.197294
        ],
        "sl": 0.199142,
        "tp": 0.191553,
        "leverage": 12,
        "po": "Пробой",
        "ATR": 0.01848,
        "ATR_rem": 0.01498,
        "price": 0.175,
        "rsi": 58.48,
        "macd": 0.002729,
        "macd_signal": 0.003872
      },
      {
        "zone": [
          0.18989,
          0.190079
        ],
        "sl": 0.191927,
        "tp": 0.184346,
        "leverage": 12,
        "po": "Пробой",
        "ATR": 0.01848,
        "ATR_rem": 0.01498,
        "price": 0.175,
        "rsi": 58.48,
        "macd": 0.002729,
        "macd_signal": 0.003872
      }
    ]
  },
  "ALGOUSDT": {
    "long": [],
    "short": [
      {
        "zone": [
          0.298598,
          0.298897
        ],
        "sl": 0.30296,
        "tp": 0.286408,
        "leverage": 12,
        "po": "Пробой",
        "ATR": 0.040635,
        "ATR_rem": 0.022435,
        "price": 0.2688,
        "rsi": 53.75,
        "macd": 0.003984,
        "macd_signal": 0.005486
      },
      {
        "zone": [
          0.279479,
          0.279758
        ],
        "sl": 0.283822,
        "tp": 0.267288,
        "leverage": 12,
        "po": "Пробой",
        "ATR": 0.040635,
        "ATR_rem": 0.022435,
        "price": 0.2688,
        "rsi": 53.75,
        "macd": 0.003984,
        "macd_signal": 0.005486
      },
      {
        "zone": [
          0.3007,
          0.301001
        ],
        "sl": 0.305064,
        "tp": 0.28851,
        "leverage": 12,
        "po": "Пробой",
        "ATR": 0.040635,
        "ATR_rem": 0.022435,
        "price": 0.2688,
        "rsi": 53.75,
        "macd": 0.003984,
        "macd_signal": 0.005486
      },
      {
        "zone": [
          0.286086,
          0.286372
        ],
        "sl": 0.290436,
        "tp": 0.273896,
        "leverage": 12,
        "po": "Пробой",
        "ATR": 0.040635,
        "ATR_rem": 0.022435,
        "price": 0.2688,
        "rsi": 53.75,
        "macd": 0.003984,
        "macd_signal": 0.005486
      },
      {
        "zone": [
          0.312212,
          0.312524
        ],
        "sl": 0.316588,
        "tp": 0.300022,
        "leverage": 12,
        "po": "Пробой",
        "ATR": 0.040635,
        "ATR_rem": 0.022435,
        "price": 0.2688,
        "rsi": 53.75,
        "macd": 0.003984,
        "macd_signal": 0.005486
      },
      {
        "zone": [
          0.307307,
          0.307614
        ],
        "sl": 0.311678,
        "tp": 0.295116,
        "leverage": 12,
        "po": "Пробой",
        "ATR": 0.040635,
        "ATR_rem": 0.022435,
        "price": 0.2688,
        "rsi": 53.75,
        "macd": 0.003984,
        "macd_signal": 0.005486
      },
      {
        "zone": [
          0.3005,
          0.3008
        ],
        "sl": 0.304864,
        "tp": 0.28831,
        "leverage": 12,
        "po": "Пробой",
        "ATR": 0.040635,
        "ATR_rem": 0.022435,
        "price": 0.2688,
        "rsi": 53.75,
        "macd": 0.003984,
        "macd_signal": 0.005486
      }
    ]
  },
  "BRETTUSDT": {
    "long": [],
    "short": [
      {
        "zone": [
          0.066566,
          0.066633
        ],
        "sl": 0.06751,
        "tp": 0.063936,
        "leverage": 12,
        "po": "Пробой",
        "ATR": 0.008768,
        "ATR_rem": 0.007648,
        "price": 0.05759,
        "rsi": 51.45,
        "macd": 0.000223,
        "macd_signal": 0.000695
      },
      {
        "zone": [
          0.066767,
          0.066833
        ],
        "sl": 0.06771,
        "tp": 0.064137,
        "leverage": 12,
        "po": "Пробой",
        "ATR": 0.008768,
        "ATR_rem": 0.007648,
        "price": 0.05759,
        "rsi": 51.45,
        "macd": 0.000223,
        "macd_signal": 0.000695
      },
      {
        "zone": [
          0.05966,
          0.059719
        ],
        "sl": 0.060596,
        "tp": 0.05703,
        "leverage": 12,
        "po": "Пробой",
        "ATR": 0.008768,
        "ATR_rem": 0.007648,
        "price": 0.05759,
        "rsi": 51.45,
        "macd": 0.000223,
        "macd_signal": 0.000695
      },
      {
        "zone": [
          0.065065,
          0.06513
        ],
        "sl": 0.066007,
        "tp": 0.062435,
        "leverage": 12,
        "po": "Пробой",
        "ATR": 0.008768,
        "ATR_rem": 0.007648,
        "price": 0.05759,
        "rsi": 51.45,
        "macd": 0.000223,
        "macd_signal": 0.000695
      },
      {
        "zone": [
          0.058158,
          0.058216
        ],
        "sl": 0.059093,
        "tp": 0.055528,
        "leverage": 12,
        "po": "Пробой",
        "ATR": 0.008768,
        "ATR_rem": 0.007648,
        "price": 0.05759,
        "rsi": 51.45,
        "macd": 0.000223,
        "macd_signal": 0.000695
      },
      {
        "zone": [
          0.064765,
          0.064829
        ],
        "sl": 0.065706,
        "tp": 0.062135,
        "leverage": 12,
        "po": "Пробой",
        "ATR": 0.008768,
        "ATR_rem": 0.007648,
        "price": 0.05759,
        "rsi": 51.45,
        "macd": 0.000223,
        "macd_signal": 0.000695
      },
      {
        "zone": [
          0.066867,
          0.066934
        ],
        "sl": 0.067811,
        "tp": 0.064237,
        "leverage": 12,
        "po": "Пробой",
        "ATR": 0.008768,
        "ATR_rem": 0.007648,
        "price": 0.05759,
        "rsi": 51.45,
        "macd": 0.000223,
        "macd_signal": 0.000695
      },
      {
        "zone": [
          0.05976,
          0.059819
        ],
        "sl": 0.060696,
        "tp": 0.05713,
        "leverage": 12,
        "po": "Пробой",
        "ATR": 0.008768,
        "ATR_rem": 0.007648,
        "price": 0.05759,
        "rsi": 51.45,
        "macd": 0.000223,
        "macd_signal": 0.000695
      },
      {
        "zone": [
          0.058258,
          0.058316
        ],
        "sl": 0.059193,
        "tp": 0.055628,
        "leverage": 12,
        "po": "Пробой",
        "ATR": 0.008768,
        "ATR_rem": 0.007648,
        "price": 0.05759,
        "rsi": 51.45,
        "macd": 0.000223,
        "macd_signal": 0.000695
      },
      {
        "zone": [
          0.058759,
          0.058817
        ],
        "sl": 0.059694,
        "tp": 0.056129,
        "leverage": 12,
        "po": "Пробой",
        "ATR": 0.008768,
        "ATR_rem": 0.007648,
        "price": 0.05759,
        "rsi": 51.45,
        "macd": 0.000223,
        "macd_signal": 0.000695
      },
      {
        "zone": [
          0.066466,
          0.066533
        ],
        "sl": 0.06741,
        "tp": 0.063836,
        "leverage": 12,
        "po": "Пробой",
        "ATR": 0.008768,
        "ATR_rem": 0.007648,
        "price": 0.05759,
        "rsi": 51.45,
        "macd": 0.000223,
        "macd_signal": 0.000695
      },
      {
        "zone": [
          0.061461,
          0.061523
        ],
        "sl": 0.0624,
        "tp": 0.058831,
        "leverage": 12,
        "po": "Пробой",
        "ATR": 0.008768,
        "ATR_rem": 0.007648,
        "price": 0.05759,
        "rsi": 51.45,
        "macd": 0.000223,
        "macd_signal": 0.000695
      }
    ]
  },
  "BTCPERP": {
    "long": [],
    "short": [
      {
        "zone": [
          119833.5138,
          119953.2276
        ],
        "sl": 120220.9461,
        "tp": 119030.3583,
        "leverage": 12,
        "po": "Пробой",
        "ATR": 2677.185,
        "ATR_rem": 2107.685,
        "price": 118733.3,
        "rsi": 53.22,
        "macd": 308.428215,
        "macd_signal": 418.809442
      },
      {
        "zone": [
          119070.4515,
          119189.403
        ],
        "sl": 119457.1215,
        "tp": 118267.296,
        "leverage": 12,
        "po": "Пробой",
        "ATR": 2677.185,
        "ATR_rem": 2107.685,
        "price": 118733.3,
        "rsi": 53.22,
        "macd": 308.428215,
        "macd_signal": 418.809442
      },
      {
        "zone": [
          118924.1053,
          119042.9106
        ],
        "sl": 119310.6291,
        "tp": 118120.9498,
        "leverage": 12,
        "po": "Пробой",
        "ATR": 2677.185,
        "ATR_rem": 2107.685,
        "price": 118733.3,
        "rsi": 53.22,
        "macd": 308.428215,
        "macd_signal": 418.809442
      },
      {
        "zone": [
          120465.7454,
          120586.0908
        ],
        "sl": 120853.8093,
        "tp": 119662.5899,
        "leverage": 12,
        "po": "Пробой",
        "ATR": 2677.185,
        "ATR_rem": 2107.685,
        "price": 118733.3,
        "rsi": 53.22,
        "macd": 308.428215,
        "macd_signal": 418.809442
      }
    ]
  },
  "BTCUSDT": {
    "long": [],
    "short": [
      {
        "zone": [
          120441.321,
          120561.642
        ],
        "sl": 120836.7945,
        "tp": 119615.8635,
        "leverage": 10,
        "po": "Пробой",
        "ATR": 2751.525,
        "ATR_rem": 2161.725,
        "price": 118664.3,
        "rsi": 53.21,
        "macd": 312.012046,
        "macd_signal": 422.282512
      },
      {
        "zone": [
          119869.75,
          119989.5
        ],
        "sl": 120264.6525,
        "tp": 119044.2925,
        "leverage": 10,
        "po": "Пробой",
        "ATR": 2751.525,
        "ATR_rem": 2161.725,
        "price": 118664.3,
        "rsi": 53.21,
        "macd": 312.012046,
        "macd_signal": 422.282512
      },
      {
        "zone": [
          119049.931,
          119168.862
        ],
        "sl": 119444.0145,
        "tp": 118224.4735,
        "leverage": 10,
        "po": "Пробой",
        "ATR": 2751.525,
        "ATR_rem": 2161.725,
        "price": 118664.3,
        "rsi": 53.21,
        "macd": 312.012046,
        "macd_signal": 422.282512
      },
      {
        "zone": [
          118867.3486,
          118986.0972
        ],
        "sl": 119261.2497,
        "tp": 118041.8911,
        "leverage": 10,
        "po": "Пробой",
        "ATR": 2751.525,
        "ATR_rem": 2161.725,
        "price": 118664.3,
        "rsi": 53.21,
        "macd": 312.012046,
        "macd_signal": 422.282512
      }
    ]
  },
  "FARTCOINUSDT": {
    "long": [],
    "short": [
      {
        "zone": [
          1.697095,
          1.698791
        ],
        "sl": 1.71766,
        "tp": 1.64049,
        "leverage": 12,
        "po": "Пробой",
        "ATR": 0.188685,
        "ATR_rem": 0.156885,
        "price": 1.5291,
        "rsi": 57.69,
        "macd": 0.015238,
        "macd_signal": 0.016712
      },
      {
        "zone": [
          1.658056,
          1.659713
        ],
        "sl": 1.678582,
        "tp": 1.60145,
        "leverage": 12,
        "po": "Пробой",
        "ATR": 0.188685,
        "ATR_rem": 0.156885,
        "price": 1.5291,
        "rsi": 57.69,
        "macd": 0.015238,
        "macd_signal": 0.016712
      },
      {
        "zone": [
          1.694993,
          1.696687
        ],
        "sl": 1.715556,
        "tp": 1.638388,
        "leverage": 12,
        "po": "Пробой",
        "ATR": 0.188685,
        "ATR_rem": 0.156885,
        "price": 1.5291,
        "rsi": 57.69,
        "macd": 0.015238,
        "macd_signal": 0.016712
      },
      {
        "zone": [
          1.598297,
          1.599893
        ],
        "sl": 1.618762,
        "tp": 1.541692,
        "leverage": 12,
        "po": "Пробой",
        "ATR": 0.188685,
        "ATR_rem": 0.156885,
        "price": 1.5291,
        "rsi": 57.69,
        "macd": 0.015238,
        "macd_signal": 0.016712
      },
      {
        "zone": [
          1.630529,
          1.632158
        ],
        "sl": 1.651026,
        "tp": 1.573923,
        "leverage": 12,
        "po": "Пробой",
        "ATR": 0.188685,
        "ATR_rem": 0.156885,
        "price": 1.5291,
        "rsi": 57.69,
        "macd": 0.015238,
        "macd_signal": 0.016712
      },
      {
        "zone": [
          1.587085,
          1.588671
        ],
        "sl": 1.60754,
        "tp": 1.53048,
        "leverage": 12,
        "po": "Пробой",
        "ATR": 0.188685,
        "ATR_rem": 0.156885,
        "price": 1.5291,
        "rsi": 57.69,
        "macd": 0.015238,
        "macd_signal": 0.016712
      }
    ]
  },
  "HYPERUSDT": {
    "long": [],
    "short": [
      {
        "zone": [
          0.479479,
          0.479958
        ],
        "sl": 0.481911,
        "tp": 0.47362,
        "leverage": 12,
        "po": "Пробой",
        "ATR": 0.01953,
        "ATR_rem": 0.01463,
        "price": 0.388,
        "rsi": 53.79,
        "macd": 0.002429,
        "macd_signal": 0.003775
      },
      {
        "zone": [
          0.396896,
          0.397293
        ],
        "sl": 0.399246,
        "tp": 0.391037,
        "leverage": 12,
        "po": "Пробой",
        "ATR": 0.01953,
        "ATR_rem": 0.01463,
        "price": 0.388,
        "rsi": 53.79,
        "macd": 0.002429,
        "macd_signal": 0.003775
      }
    ]
  },
  "HYPEUSDT": {
    "long": [],
    "short": [
      {
        "zone": [
          45.67563,
          45.72126
        ],
        "sl": 46.0308,
        "tp": 44.74701,
        "leverage": 12,
        "po": "Пробой",
        "ATR": 3.0954,
        "ATR_rem": 2.6154,
        "price": 43.926,
        "rsi": 56.73,
        "macd": 0.254327,
        "macd_signal": 0.32327
      },
      {
        "zone": [
          46.359313,
          46.405626
        ],
        "sl": 46.715166,
        "tp": 45.430693,
        "leverage": 12,
        "po": "Пробой",
        "ATR": 3.0954,
        "ATR_rem": 2.6154,
        "price": 43.926,
        "rsi": 56.73,
        "macd": 0.254327,
        "macd_signal": 0.32327
      },
      {
        "zone": [
          45.7457,
          45.7914
        ],
        "sl": 46.10094,
        "tp": 44.81708,
        "leverage": 12,
        "po": "Пробой",
        "ATR": 3.0954,
        "ATR_rem": 2.6154,
        "price": 43.926,
        "rsi": 56.73,
        "macd": 0.254327,
        "macd_signal": 0.32327
      },
      {
        "zone": [
          45.409364,
          45.454728
        ],
        "sl": 45.764268,
        "tp": 44.480744,
        "leverage": 12,
        "po": "Пробой",
        "ATR": 3.0954,
        "ATR_rem": 2.6154,
        "price": 43.926,
        "rsi": 56.73,
        "macd": 0.254327,
        "macd_signal": 0.32327
      },
      {
        "zone": [
          47.872825,
          47.92065
        ],
        "sl": 48.23019,
        "tp": 46.944205,
        "leverage": 12,
        "po": "Пробой",
        "ATR": 3.0954,
        "ATR_rem": 2.6154,
        "price": 43.926,
        "rsi": 56.73,
        "macd": 0.254327,
        "macd_signal": 0.32327
      },
      {
        "zone": [
          45.292247,
          45.337494
        ],
        "sl": 45.647034,
        "tp": 44.363627,
        "leverage": 12,
        "po": "Пробой",
        "ATR": 3.0954,
        "ATR_rem": 2.6154,
        "price": 43.926,
        "rsi": 56.73,
        "macd": 0.254327,
        "macd_signal": 0.32327
      },
      {
        "zone": [
          47.443396,
          47.490792
        ],
        "sl": 47.800332,
        "tp": 46.514776,
        "leverage": 12,
        "po": "Пробой",
        "ATR": 3.0954,
        "ATR_rem": 2.6154,
        "price": 43.926,
        "rsi": 56.73,
        "macd": 0.254327,
        "macd_signal": 0.32327
      }
    ]
  },
  "LAUNCHCOINUSDT": {
    "long": [],
    "short": [
      {
        "zone": [
          0.090791,
          0.090881
        ],
        "sl": 0.093105,
        "tp": 0.084119,
        "leverage": 12,
        "po": "Пробой",
        "ATR": 0.022239,
        "ATR_rem": 0.019289,
        "price": 0.07391,
        "rsi": 53.13,
        "macd": 0.003082,
        "macd_signal": 0.004179
      },
      {
        "zone": [
          0.102903,
          0.103006
        ],
        "sl": 0.10523,
        "tp": 0.096231,
        "leverage": 12,
        "po": "Пробой",
        "ATR": 0.022239,
        "ATR_rem": 0.019289,
        "price": 0.07391,
        "rsi": 53.13,
        "macd": 0.003082,
        "macd_signal": 0.004179
      },
      {
        "zone": [
          0.076777,
          0.076853
        ],
        "sl": 0.079077,
        "tp": 0.070105,
        "leverage": 12,
        "po": "Пробой",
        "ATR": 0.022239,
        "ATR_rem": 0.019289,
        "price": 0.07391,
        "rsi": 53.13,
        "macd": 0.003082,
        "macd_signal": 0.004179
      },
      {
        "zone": [
          0.1004,
          0.100501
        ],
        "sl": 0.102725,
        "tp": 0.093728,
        "leverage": 12,
        "po": "Пробой",
        "ATR": 0.022239,
        "ATR_rem": 0.019289,
        "price": 0.07391,
        "rsi": 53.13,
        "macd": 0.003082,
        "macd_signal": 0.004179
      },
      {
        "zone": [
          0.119619,
          0.119739
        ],
        "sl": 0.121963,
        "tp": 0.112947,
        "leverage": 12,
        "po": "Пробой",
        "ATR": 0.022239,
        "ATR_rem": 0.019289,
        "price": 0.07391,
        "rsi": 53.13,
        "macd": 0.003082,
        "macd_signal": 0.004179
      },
      {
        "zone": [
          0.115616,
          0.115731
        ],
        "sl": 0.117955,
        "tp": 0.108944,
        "leverage": 12,
        "po": "Пробой",
        "ATR": 0.022239,
        "ATR_rem": 0.019289,
        "price": 0.07391,
        "rsi": 53.13,
        "macd": 0.003082,
        "macd_signal": 0.004179
      },
      {
        "zone": [
          0.091091,
          0.091182
        ],
        "sl": 0.093406,
        "tp": 0.084419,
        "leverage": 12,
        "po": "Пробой",
        "ATR": 0.022239,
        "ATR_rem": 0.019289,
        "price": 0.07391,
        "rsi": 53.13,
        "macd": 0.003082,
        "macd_signal": 0.004179
      },
      {
        "zone": [
          0.1001,
          0.1002
        ],
        "sl": 0.102424,
        "tp": 0.093428,
        "leverage": 12,
        "po": "Пробой",
        "ATR": 0.022239,
        "ATR_rem": 0.019289,
        "price": 0.07391,
        "rsi": 53.13,
        "macd": 0.003082,
        "macd_signal": 0.004179
      },
      {
        "zone": [
          0.090691,
          0.090781
        ],
        "sl": 0.093005,
        "tp": 0.084019,
        "leverage": 12,
        "po": "Пробой",
        "ATR": 0.022239,
        "ATR_rem": 0.019289,
        "price": 0.07391,
        "rsi": 53.13,
        "macd": 0.003082,
        "macd_signal": 0.004179
      },
      {
        "zone": [
          0.114414,
          0.114529
        ],
        "sl": 0.116753,
        "tp": 0.107742,
        "leverage": 12,
        "po": "Пробой",
        "ATR": 0.022239,
        "ATR_rem": 0.019289,
        "price": 0.07391,
        "rsi": 53.13,
        "macd": 0.003082,
        "macd_signal": 0.004179
      },
      {
        "zone": [
          0.108308,
          0.108416
        ],
        "sl": 0.11064,
        "tp": 0.101636,
        "leverage": 12,
        "po": "Пробой",
        "ATR": 0.022239,
        "ATR_rem": 0.019289,
        "price": 0.07391,
        "rsi": 53.13,
        "macd": 0.003082,
        "macd_signal": 0.004179
      }
    ]
  },
  "PENGUUSDT": {
    "long": [
      {
        "zone": [
          0.040219,
          0.04026
        ],
        "sl": 0.039852,
        "tp": 0.04136,
        "leverage": 12,
        "po": "Отбой",
        "ATR": 0.003668,
        "ATR_rem": 0.003113,
        "price": 0.043256,
        "rsi": 49.71,
        "macd": -7.1e-05,
        "macd_signal": -9.5e-05
      },
      {
        "zone": [
          0.035828,
          0.035864
        ],
        "sl": 0.035461,
        "tp": 0.036964,
        "leverage": 12,
        "po": "Отбой",
        "ATR": 0.003668,
        "ATR_rem": 0.003113,
        "price": 0.043256,
        "rsi": 49.71,
        "macd": -7.1e-05,
        "macd_signal": -9.5e-05
      },
      {
        "zone": [
          0.031936,
          0.031968
        ],
        "sl": 0.031569,
        "tp": 0.033068,
        "leverage": 12,
        "po": "Отбой",
        "ATR": 0.003668,
        "ATR_rem": 0.003113,
        "price": 0.043256,
        "rsi": 49.71,
        "macd": -7.1e-05,
        "macd_signal": -9.5e-05
      },
      {
        "zone": [
          0.030439,
          0.03047
        ],
        "sl": 0.030072,
        "tp": 0.03157,
        "leverage": 12,
        "po": "Отбой",
        "ATR": 0.003668,
        "ATR_rem": 0.003113,
        "price": 0.043256,
        "rsi": 49.71,
        "macd": -7.1e-05,
        "macd_signal": -9.5e-05
      },
      {
        "zone": [
          0.031537,
          0.031568
        ],
        "sl": 0.03117,
        "tp": 0.032668,
        "leverage": 12,
        "po": "Отбой",
        "ATR": 0.003668,
        "ATR_rem": 0.003113,
        "price": 0.043256,
        "rsi": 49.71,
        "macd": -7.1e-05,
        "macd_signal": -9.5e-05
      },
      {
        "zone": [
          0.030539,
          0.030569
        ],
        "sl": 0.030172,
        "tp": 0.031669,
        "leverage": 12,
        "po": "Отбой",
        "ATR": 0.003668,
        "ATR_rem": 0.003113,
        "price": 0.043256,
        "rsi": 49.71,
        "macd": -7.1e-05,
        "macd_signal": -9.5e-05
      },
      {
        "zone": [
          0.038423,
          0.038462
        ],
        "sl": 0.038056,
        "tp": 0.039562,
        "leverage": 12,
        "po": "Отбой",
        "ATR": 0.003668,
        "ATR_rem": 0.003113,
        "price": 0.043256,
        "rsi": 49.71,
        "macd": -7.1e-05,
        "macd_signal": -9.5e-05
      },
      {
        "zone": [
          0.035529,
          0.035564
        ],
        "sl": 0.035162,
        "tp": 0.036664,
        "leverage": 12,
        "po": "Отбой",
        "ATR": 0.003668,
        "ATR_rem": 0.003113,
        "price": 0.043256,
        "rsi": 49.71,
        "macd": -7.1e-05,
        "macd_signal": -9.5e-05
      },
      {
        "zone": [
          0.031637,
          0.031668
        ],
        "sl": 0.03127,
        "tp": 0.032768,
        "leverage": 12,
        "po": "Отбой",
        "ATR": 0.003668,
        "ATR_rem": 0.003113,
        "price": 0.043256,
        "rsi": 49.71,
        "macd": -7.1e-05,
        "macd_signal": -9.5e-05
      },
      {
        "zone": [
          0.03004,
          0.03007
        ],
        "sl": 0.029673,
        "tp": 0.03117,
        "leverage": 12,
        "po": "Отбой",
        "ATR": 0.003668,
        "ATR_rem": 0.003113,
        "price": 0.043256,
        "rsi": 49.71,
        "macd": -7.1e-05,
        "macd_signal": -9.5e-05
      },
      {
        "zone": [
          0.030639,
          0.030669
        ],
        "sl": 0.030272,
        "tp": 0.031769,
        "leverage": 12,
        "po": "Отбой",
        "ATR": 0.003668,
        "ATR_rem": 0.003113,
        "price": 0.043256,
        "rsi": 49.71,
        "macd": -7.1e-05,
        "macd_signal": -9.5e-05
      }
    ],
    "short": []
  },
  "POPCATUSDT": {
    "long": [],
    "short": [
      {
        "zone": [
          0.489289,
          0.489778
        ],
        "sl": 0.494472,
        "tp": 0.475208,
        "leverage": 12,
        "po": "Пробой",
        "ATR": 0.046935,
        "ATR_rem": 0.039735,
        "price": 0.3951,
        "rsi": 54.9,
        "macd": 0.00278,
        "macd_signal": 0.004149
      },
      {
        "zone": [
          0.402802,
          0.403205
        ],
        "sl": 0.407898,
        "tp": 0.388722,
        "leverage": 12,
        "po": "Пробой",
        "ATR": 0.046935,
        "ATR_rem": 0.039735,
        "price": 0.3951,
        "rsi": 54.9,
        "macd": 0.00278,
        "macd_signal": 0.004149
      },
      {
        "zone": [
          0.459559,
          0.460018
        ],
        "sl": 0.464712,
        "tp": 0.445478,
        "leverage": 12,
        "po": "Пробой",
        "ATR": 0.046935,
        "ATR_rem": 0.039735,
        "price": 0.3951,
        "rsi": 54.9,
        "macd": 0.00278,
        "macd_signal": 0.004149
      },
      {
        "zone": [
          0.448248,
          0.448696
        ],
        "sl": 0.45339,
        "tp": 0.434168,
        "leverage": 12,
        "po": "Пробой",
        "ATR": 0.046935,
        "ATR_rem": 0.039735,
        "price": 0.3951,
        "rsi": 54.9,
        "macd": 0.00278,
        "macd_signal": 0.004149
      },
      {
        "zone": [
          0.412112,
          0.412523
        ],
        "sl": 0.417216,
        "tp": 0.398032,
        "leverage": 12,
        "po": "Пробой",
        "ATR": 0.046935,
        "ATR_rem": 0.039735,
        "price": 0.3951,
        "rsi": 54.9,
        "macd": 0.00278,
        "macd_signal": 0.004149
      },
      {
        "zone": [
          0.447247,
          0.447694
        ],
        "sl": 0.452388,
        "tp": 0.433166,
        "leverage": 12,
        "po": "Пробой",
        "ATR": 0.046935,
        "ATR_rem": 0.039735,
        "price": 0.3951,
        "rsi": 54.9,
        "macd": 0.00278,
        "macd_signal": 0.004149
      },
      {
        "zone": [
          0.395695,
          0.396091
        ],
        "sl": 0.400785,
        "tp": 0.381614,
        "leverage": 12,
        "po": "Пробой",
        "ATR": 0.046935,
        "ATR_rem": 0.039735,
        "price": 0.3951,
        "rsi": 54.9,
        "macd": 0.00278,
        "macd_signal": 0.004149
      },
      {
        "zone": [
          0.396296,
          0.396692
        ],
        "sl": 0.401386,
        "tp": 0.382216,
        "leverage": 12,
        "po": "Пробой",
        "ATR": 0.046935,
        "ATR_rem": 0.039735,
        "price": 0.3951,
        "rsi": 54.9,
        "macd": 0.00278,
        "macd_signal": 0.004149
      }
    ]
  },
  "SPXUSDT": {
    "long": [],
    "short": [
      {
        "zone": [
          1.898997,
          1.900894
        ],
        "sl": 1.919322,
        "tp": 1.843715,
        "leverage": 12,
        "po": "Пробой",
        "ATR": 0.184275,
        "ATR_rem": 0.145475,
        "price": 1.8773,
        "rsi": 52.51,
        "macd": 0.01252,
        "macd_signal": 0.013777
      },
      {
        "zone": [
          2.062861,
          2.064922
        ],
        "sl": 2.08335,
        "tp": 2.007578,
        "leverage": 12,
        "po": "Пробой",
        "ATR": 0.184275,
        "ATR_rem": 0.145475,
        "price": 1.8773,
        "rsi": 52.51,
        "macd": 0.01252,
        "macd_signal": 0.013777
      },
      {
        "zone": [
          1.96206,
          1.96402
        ],
        "sl": 1.982448,
        "tp": 1.906778,
        "leverage": 12,
        "po": "Пробой",
        "ATR": 0.184275,
        "ATR_rem": 0.145475,
        "price": 1.8773,
        "rsi": 52.51,
        "macd": 0.01252,
        "macd_signal": 0.013777
      },
      {
        "zone": [
          2.03203,
          2.03406
        ],
        "sl": 2.052488,
        "tp": 1.976747,
        "leverage": 12,
        "po": "Пробой",
        "ATR": 0.184275,
        "ATR_rem": 0.145475,
        "price": 1.8773,
        "rsi": 52.51,
        "macd": 0.01252,
        "macd_signal": 0.013777
      },
      {
        "zone": [
          2.035133,
          2.037166
        ],
        "sl": 2.055594,
        "tp": 1.979851,
        "leverage": 12,
        "po": "Пробой",
        "ATR": 0.184275,
        "ATR_rem": 0.145475,
        "price": 1.8773,
        "rsi": 52.51,
        "macd": 0.01252,
        "macd_signal": 0.013777
      },
      {
        "zone": [
          2.038036,
          2.040072
        ],
        "sl": 2.0585,
        "tp": 1.982754,
        "leverage": 12,
        "po": "Пробой",
        "ATR": 0.184275,
        "ATR_rem": 0.145475,
        "price": 1.8773,
        "rsi": 52.51,
        "macd": 0.01252,
        "macd_signal": 0.013777
      }
    ]
  },
  "SUIUSDT": {
    "long": [],
    "short": [
      {
        "zone": [
          3.805101,
          3.808903
        ],
        "sl": 3.84476,
        "tp": 3.697528,
        "leverage": 12,
        "po": "Пробой",
        "ATR": 0.358575,
        "ATR_rem": 0.321475,
        "price": 3.7196,
        "rsi": 54.92,
        "macd": 0.027471,
        "macd_signal": 0.042737
      },
      {
        "zone": [
          4.039535,
          4.043571
        ],
        "sl": 4.079428,
        "tp": 3.931962,
        "leverage": 12,
        "po": "Пробой",
        "ATR": 0.358575,
        "ATR_rem": 0.321475,
        "price": 3.7196,
        "rsi": 54.92,
        "macd": 0.027471,
        "macd_signal": 0.042737
      },
      {
        "zone": [
          3.924921,
          3.928842
        ],
        "sl": 3.9647,
        "tp": 3.817348,
        "leverage": 12,
        "po": "Пробой",
        "ATR": 0.358575,
        "ATR_rem": 0.321475,
        "price": 3.7196,
        "rsi": 54.92,
        "macd": 0.027471,
        "macd_signal": 0.042737
      },
      {
        "zone": [
          4.103599,
          4.107699
        ],
        "sl": 4.143556,
        "tp": 3.996026,
        "leverage": 12,
        "po": "Пробой",
        "ATR": 0.358575,
        "ATR_rem": 0.321475,
        "price": 3.7196,
        "rsi": 54.92,
        "macd": 0.027471,
        "macd_signal": 0.042737
      },
      {
        "zone": [
          4.032929,
          4.036958
        ],
        "sl": 4.072816,
        "tp": 3.925357,
        "leverage": 12,
        "po": "Пробой",
        "ATR": 0.358575,
        "ATR_rem": 0.321475,
        "price": 3.7196,
        "rsi": 54.92,
        "macd": 0.027471,
        "macd_signal": 0.042737
      },
      {
        "zone": [
          3.965662,
          3.969623
        ],
        "sl": 4.00548,
        "tp": 3.85809,
        "leverage": 12,
        "po": "Пробой",
        "ATR": 0.358575,
        "ATR_rem": 0.321475,
        "price": 3.7196,
        "rsi": 54.92,
        "macd": 0.027471,
        "macd_signal": 0.042737
      },
      {
        "zone": [
          3.810407,
          3.814213
        ],
        "sl": 3.85007,
        "tp": 3.702835,
        "leverage": 12,
        "po": "Пробой",
        "ATR": 0.358575,
        "ATR_rem": 0.321475,
        "price": 3.7196,
        "rsi": 54.92,
        "macd": 0.027471,
        "macd_signal": 0.042737
      },
      {
        "zone": [
          4.040637,
          4.044673
        ],
        "sl": 4.08053,
        "tp": 3.933065,
        "leverage": 12,
        "po": "Пробой",
        "ATR": 0.358575,
        "ATR_rem": 0.321475,
        "price": 3.7196,
        "rsi": 54.92,
        "macd": 0.027471,
        "macd_signal": 0.042737
      }
    ]
  },
  "TAOUSDT": {
    "long": [],
    "short": [
      {
        "zone": [
          455.455,
          455.91
        ],
        "sl": 458.78385,
        "tp": 446.83345,
        "leverage": 12,
        "po": "Пробой",
        "ATR": 28.7385,
        "ATR_rem": 22.2985,
        "price": 427.03,
        "rsi": 57.03,
        "macd": 2.332622,
        "macd_signal": 2.983242
      },
      {
        "zone": [
          462.39193,
          462.85386
        ],
        "sl": 465.72771,
        "tp": 453.77038,
        "leverage": 12,
        "po": "Пробой",
        "ATR": 28.7385,
        "ATR_rem": 22.2985,
        "price": 427.03,
        "rsi": 57.03,
        "macd": 2.332622,
        "macd_signal": 2.983242
      },
      {
        "zone": [
          435.94551,
          436.38102
        ],
        "sl": 439.25487,
        "tp": 427.32396,
        "leverage": 12,
        "po": "Пробой",
        "ATR": 28.7385,
        "ATR_rem": 22.2985,
        "price": 427.03,
        "rsi": 57.03,
        "macd": 2.332622,
        "macd_signal": 2.983242
      },
      {
        "zone": [
          444.58414,
          445.02828
        ],
        "sl": 447.90213,
        "tp": 435.96259,
        "leverage": 12,
        "po": "Пробой",
        "ATR": 28.7385,
        "ATR_rem": 22.2985,
        "price": 427.03,
        "rsi": 57.03,
        "macd": 2.332622,
        "macd_signal": 2.983242
      }
    ]
  },
  "last_updated": "2025-07-24 06:38:36"
}