{
  "last_updated": "2025-07-15 20:25:10",
  "BTCUSDT": {
    "long": [
      {
        "zone": [
          117000,
          117300
        ],
        "tp": 121000,
        "sl": 115000,
        "leverage": "10"
      }
    ],
    "short": [
      {
        "zone": [
          119200,
          119500
        ],
        "tp": 116500,
        "sl": 120500,
        "leverage": "10"
      }
    ]
  },
  "ETHUSDT": {
    "long": [
      {
        "zone": [
          2900,
          2920
        ],
        "tp": 3000,
        "sl": 2850,
        "leverage": "8"
      }
    ],
    "short": [
      {
        "zone": [
          2980,
          3000
        ],
        "tp": 2900,
        "sl": 3050,
        "leverage": "8"
      }
    ]
  },
  "MOODENGUSDT": {
    "long": [
      {
        "zone": [
          0.18,
          0.183
        ],
        "tp": 0.195,
        "sl": 0.175,
        "leverage": "12"
      }
    ],
    "short": [
      {
        "zone": [
          0.193,
          0.196
        ],
        "tp": 0.182,
        "sl": 0.2,
        "leverage": "12"
      }
    ]
  },
  "TUTUSDT": {
    "long": [
      {
        "zone": [
          1.05,
          1.08
        ],
        "tp": 1.14,
        "sl": 1.02,
        "leverage": "15"
      }
    ],
    "short": [
      {
        "zone": [
          1.12,
          1.15
        ],
        "tp": 1.07,
        "sl": 1.18,
        "leverage": "15"
      }
    ]
  },
  "BNBUSDT": {
    "long": [
      {
        "zone": [
          305,
          308
        ],
        "tp": 314,
        "sl": 300,
        "leverage": "7"
      }
    ],
    "short": [
      {
        "zone": [
          316,
          319
        ],
        "tp": 308,
        "sl": 322,
        "leverage": "7"
      }
    ]
  },
  "SOLUSDT": {
    "long": [
      {
        "zone": [
          164,
          166
        ],
        "tp": 172,
        "sl": 160,
        "leverage": "9"
      }
    ],
    "short": [
      {
        "zone": [
          172,
          175
        ],
        "tp": 165,
        "sl": 178,
        "leverage": "9"
      }
    ]
  },
  "RPUSDT": {
    "long": [
      {
        "zone": [
          0.565,
          0.575
        ],
        "tp": 0.6,
        "sl": 0.55,
        "leverage": "10"
      }
    ],
    "short": [
      {
        "zone": [
          0.595,
          0.605
        ],
        "tp": 0.575,
        "sl": 0.615,
        "leverage": "10"
      }
    ]
  },
  "TRUSDT": {
    "long": [
      {
        "zone": [
          0.076,
          0.078
        ],
        "tp": 0.082,
        "sl": 0.074,
        "leverage": "10"
      }
    ],
    "short": [
      {
        "zone": [
          0.08,
          0.082
        ],
        "tp": 0.077,
        "sl": 0.084,
        "leverage": "10"
      }
    ]
  },
  "SUIUSDT": {
    "long": [
      {
        "zone": [
          2.48,
          2.52
        ],
        "tp": 2.6,
        "sl": 2.44,
        "leverage": "10"
      }
    ],
    "short": [
      {
        "zone": [
          2.65,
          2.7
        ],
        "tp": 2.57,
        "sl": 2.75,
        "leverage": "10"
      }
    ]
  },
  "ADAUSDT": {
    "long": [
      {
        "zone": [
          0.675,
          0.685
        ],
        "tp": 0.705,
        "sl": 0.66,
        "leverage": "10"
      }
    ],
    "short": [
      {
        "zone": [
          0.705,
          0.715
        ],
        "tp": 0.685,
        "sl": 0.73,
        "leverage": "10"
      }
    ]
  },
  "PLUMEUSDT": {
    "long": [
      {
        "zone": [
          0.108,
          0.112
        ],
        "tp": 0.118,
        "sl": 0.105,
        "leverage": "10"
      }
    ],
    "short": [
      {
        "zone": [
          0.12,
          0.124	
        ],
        "tp": 0.114,
        "sl": 0.128,
        "leverage": "10"
      }
    ]
  }
}
